<?xml version="1.0" encoding="utf-8"?>
<ArrayOfEngineer>
  <Engineer>
    <Id>375885354</Id>
    <Name>Dani Levi</Name>
    <Email>375885354@gmail.com</Email>
    <Level>AdvancedBeginner</Level>
    <Cost>200.35</Cost>
  </Engineer>
  <Engineer>
    <Id>225802200</Id>
    <Name>Eli Amar</Name>
    <Email>225802200@gmail.com</Email>
    <Level>AdvancedBeginner</Level>
    <Cost>200.35</Cost>
  </Engineer>
  <Engineer>
    <Id>351481396</Id>
    <Name>Yair Cohen</Name>
    <Email>351481396@gmail.com</Email>
    <Level>AdvancedBeginner</Level>
    <Cost>200.35</Cost>
  </Engineer>
  <Engineer>
    <Id>398318855</Id>
    <Name>Ariela Levin</Name>
    <Email>398318855@gmail.com</Email>
    <Level>AdvancedBeginner</Level>
    <Cost>200.35</Cost>
  </Engineer>
  <Engineer>
    <Id>324073137</Id>
    <Name>Diana Klein</Name>
    <Email>324073137@gmail.com</Email>
    <Level>AdvancedBeginner</Level>
    <Cost>200.35</Cost>
  </Engineer>
  <Engineer>
    <Id>207205384</Id>
    <Name>Dani Levi</Name>
    <Email>207205384@gmail.com</Email>
    <Level>AdvancedBeginner</Level>
    <Cost>200.35</Cost>
  </Engineer>
  <Engineer>
    <Id>316196124</Id>
    <Name>Eli Amar</Name>
    <Email>316196124@gmail.com</Email>
    <Level>AdvancedBeginner</Level>
    <Cost>200.35</Cost>
  </Engineer>
  <Engineer>
    <Id>245176036</Id>
    <Name>Yair Cohen</Name>
    <Email>245176036@gmail.com</Email>
    <Level>AdvancedBeginner</Level>
    <Cost>200.35</Cost>
  </Engineer>
  <Engineer>
    <Id>238628697</Id>
    <Name>Ariela Levin</Name>
    <Email>238628697@gmail.com</Email>
    <Level>AdvancedBeginner</Level>
    <Cost>200.35</Cost>
  </Engineer>
  <Engineer>
    <Id>274574797</Id>
    <Name>Diana Klein</Name>
    <Email>274574797@gmail.com</Email>
    <Level>AdvancedBeginner</Level>
    <Cost>200.35</Cost>
  </Engineer>
  <Engineer>
    <Id>235565738</Id>
    <Name>Dani Levi</Name>
    <Email>235565738@gmail.com</Email>
    <Level>AdvancedBeginner</Level>
    <Cost>200.35</Cost>
  </Engineer>
  <Engineer>
    <Id>304211833</Id>
    <Name>Eli Amar</Name>
    <Email>304211833@gmail.com</Email>
    <Level>AdvancedBeginner</Level>
    <Cost>200.35</Cost>
  </Engineer>
  <Engineer>
    <Id>302389220</Id>
    <Name>Yair Cohen</Name>
    <Email>302389220@gmail.com</Email>
    <Level>AdvancedBeginner</Level>
    <Cost>200.35</Cost>
  </Engineer>
  <Engineer>
    <Id>313700402</Id>
    <Name>Ariela Levin</Name>
    <Email>313700402@gmail.com</Email>
    <Level>AdvancedBeginner</Level>
    <Cost>200.35</Cost>
  </Engineer>
  <Engineer>
    <Id>339028694</Id>
    <Name>Diana Klein</Name>
    <Email>339028694@gmail.com</Email>
    <Level>AdvancedBeginner</Level>
    <Cost>200.35</Cost>
  </Engineer>
  <Engineer>
    <Id>378020410</Id>
    <Name>Dani Levi</Name>
    <Email>378020410@gmail.com</Email>
    <Level>AdvancedBeginner</Level>
    <Cost>200.35</Cost>
  </Engineer>
  <Engineer>
    <Id>292780454</Id>
    <Name>Eli Amar</Name>
    <Email>292780454@gmail.com</Email>
    <Level>AdvancedBeginner</Level>
    <Cost>200.35</Cost>
  </Engineer>
  <Engineer>
    <Id>299461494</Id>
    <Name>Yair Cohen</Name>
    <Email>299461494@gmail.com</Email>
    <Level>AdvancedBeginner</Level>
    <Cost>200.35</Cost>
  </Engineer>
  <Engineer>
    <Id>288609899</Id>
    <Name>Ariela Levin</Name>
    <Email>288609899@gmail.com</Email>
    <Level>AdvancedBeginner</Level>
    <Cost>200.35</Cost>
  </Engineer>
  <Engineer>
    <Id>208109039</Id>
    <Name>Diana Klein</Name>
    <Email>208109039@gmail.com</Email>
    <Level>AdvancedBeginner</Level>
    <Cost>200.35</Cost>
  </Engineer>
  <Engineer>
    <Id>213179153</Id>
    <Name>Dani Levi</Name>
    <Email>213179153@gmail.com</Email>
    <Level>AdvancedBeginner</Level>
    <Cost>200.35</Cost>
  </Engineer>
  <Engineer>
    <Id>249097099</Id>
    <Name>Eli Amar</Name>
    <Email>249097099@gmail.com</Email>
    <Level>AdvancedBeginner</Level>
    <Cost>200.35</Cost>
  </Engineer>
  <Engineer>
    <Id>285907253</Id>
    <Name>Yair Cohen</Name>
    <Email>285907253@gmail.com</Email>
    <Level>AdvancedBeginner</Level>
    <Cost>200.35</Cost>
  </Engineer>
  <Engineer>
    <Id>233803241</Id>
    <Name>Ariela Levin</Name>
    <Email>233803241@gmail.com</Email>
    <Level>AdvancedBeginner</Level>
    <Cost>200.35</Cost>
  </Engineer>
  <Engineer>
    <Id>377851118</Id>
    <Name>Diana Klein</Name>
    <Email>377851118@gmail.com</Email>
    <Level>AdvancedBeginner</Level>
    <Cost>200.35</Cost>
  </Engineer>
  <Engineer>
    <Id>330268799</Id>
    <Name>Dani Levi</Name>
    <Email>330268799@gmail.com</Email>
    <Level>AdvancedBeginner</Level>
    <Cost>200.35</Cost>
  </Engineer>
  <Engineer>
    <Id>331601175</Id>
    <Name>Eli Amar</Name>
    <Email>331601175@gmail.com</Email>
    <Level>AdvancedBeginner</Level>
    <Cost>200.35</Cost>
  </Engineer>
  <Engineer>
    <Id>310954527</Id>
    <Name>Yair Cohen</Name>
    <Email>310954527@gmail.com</Email>
    <Level>AdvancedBeginner</Level>
    <Cost>200.35</Cost>
  </Engineer>
  <Engineer>
    <Id>258543270</Id>
    <Name>Ariela Levin</Name>
    <Email>258543270@gmail.com</Email>
    <Level>AdvancedBeginner</Level>
    <Cost>200.35</Cost>
  </Engineer>
  <Engineer>
    <Id>334490195</Id>
    <Name>Diana Klein</Name>
    <Email>334490195@gmail.com</Email>
    <Level>AdvancedBeginner</Level>
    <Cost>200.35</Cost>
  </Engineer>
  <Engineer>
    <Id>334576398</Id>
    <Name>Dani Levi</Name>
    <Email>334576398@gmail.com</Email>
    <Level>AdvancedBeginner</Level>
    <Cost>200.35</Cost>
  </Engineer>
  <Engineer>
    <Id>246474125</Id>
    <Name>Eli Amar</Name>
    <Email>246474125@gmail.com</Email>
    <Level>AdvancedBeginner</Level>
    <Cost>200.35</Cost>
  </Engineer>
  <Engineer>
    <Id>335756619</Id>
    <Name>Yair Cohen</Name>
    <Email>335756619@gmail.com</Email>
    <Level>AdvancedBeginner</Level>
    <Cost>200.35</Cost>
  </Engineer>
  <Engineer>
    <Id>340560756</Id>
    <Name>Ariela Levin</Name>
    <Email>340560756@gmail.com</Email>
    <Level>AdvancedBeginner</Level>
    <Cost>200.35</Cost>
  </Engineer>
  <Engineer>
    <Id>229615049</Id>
    <Name>Diana Klein</Name>
    <Email>229615049@gmail.com</Email>
    <Level>AdvancedBeginner</Level>
    <Cost>200.35</Cost>
  </Engineer>
  <Engineer>
    <Id>214466112</Id>
    <Name>Dani Levi</Name>
    <Email>214466112@gmail.com</Email>
    <Level>AdvancedBeginner</Level>
    <Cost>200.35</Cost>
  </Engineer>
  <Engineer>
    <Id>347664713</Id>
    <Name>Eli Amar</Name>
    <Email>347664713@gmail.com</Email>
    <Level>AdvancedBeginner</Level>
    <Cost>200.35</Cost>
  </Engineer>
  <Engineer>
    <Id>258443026</Id>
    <Name>Yair Cohen</Name>
    <Email>258443026@gmail.com</Email>
    <Level>AdvancedBeginner</Level>
    <Cost>200.35</Cost>
  </Engineer>
  <Engineer>
    <Id>251169730</Id>
    <Name>Ariela Levin</Name>
    <Email>251169730@gmail.com</Email>
    <Level>AdvancedBeginner</Level>
    <Cost>200.35</Cost>
  </Engineer>
  <Engineer>
    <Id>307095504</Id>
    <Name>Diana Klein</Name>
    <Email>307095504@gmail.com</Email>
    <Level>AdvancedBeginner</Level>
    <Cost>200.35</Cost>
  </Engineer>
  <Engineer>
    <Id>272537190</Id>
    <Name>Dani Levi</Name>
    <Email>272537190@gmail.com</Email>
    <Level>AdvancedBeginner</Level>
    <Cost>200.35</Cost>
  </Engineer>
  <Engineer>
    <Id>319432674</Id>
    <Name>Eli Amar</Name>
    <Email>319432674@gmail.com</Email>
    <Level>AdvancedBeginner</Level>
    <Cost>200.35</Cost>
  </Engineer>
  <Engineer>
    <Id>211772638</Id>
    <Name>Yair Cohen</Name>
    <Email>211772638@gmail.com</Email>
    <Level>AdvancedBeginner</Level>
    <Cost>200.35</Cost>
  </Engineer>
  <Engineer>
    <Id>201870828</Id>
    <Name>Diana Klein</Name>
    <Email>201870828@gmail.com</Email>
    <Level>AdvancedBeginner</Level>
    <Cost>200.35</Cost>
  </Engineer>
</ArrayOfEngineer>